convertu/__init__.py
convertu/__main__.py
convertu/classification.json
convertu/convertu.py
pyconvertu-1.0.8.dist-info/licenses/LICENSE
pyconvertu-1.0.8.dist-info/METADATA
pyconvertu-1.0.8.dist-info/WHEEL
pyconvertu-1.0.8.dist-info/entry_points.txt
pyconvertu-1.0.8.dist-info/top_level.txt
pyconvertu-1.0.8.dist-info/RECORD
