Metadata-Version: 2.4
Name: pyconvertu
Version: 1.0.8
Summary: From/to Classification Converter
Author-email: The Economist <29724411+econcz@users.noreply.github.com>
License-Expression: MIT
Project-URL: Homepage, https://github.com/econcz/pyconvertu
Project-URL: Bug Tracker, https://github.com/econcz/pyconvertu/issues
Keywords: data-science,classification,converter,iso-3166-1,iso-3166-1-alpha-3,iso-3166-1-alpha-2,iso-3166-1-numeric
Classifier: Programming Language :: Python :: 3
Classifier: Programming Language :: Python :: 3.10
Classifier: Programming Language :: Python :: 3.11
Classifier: Programming Language :: Python :: 3.12
Classifier: Operating System :: OS Independent
Classifier: Topic :: Scientific/Engineering :: Information Analysis
Requires-Python: >=3.10
License-File: LICENSE
Dynamic: license-file
